robin_sd_upload/__init__.py
robin_sd_upload/__main__.py
robin_sd_upload/_version.py
robin_sd_upload/api_interaction/__init__.py
robin_sd_upload/api_interaction/check_software.py
robin_sd_upload/api_interaction/get_bearer_token.py
robin_sd_upload/api_interaction/push_software.py
robin_sd_upload/slack_interaction/__init__.py
robin_sd_upload/slack_interaction/slack_handler.py
robin_sd_upload/supportive_scripts/__init__.py
robin_sd_upload/supportive_scripts/arg_parse.py
robin_sd_upload/supportive_scripts/check_upload_file.py
robin_sd_upload/supportive_scripts/create_folder.py
robin_sd_upload/supportive_scripts/create_zip.py
robin_sd_upload/supportive_scripts/logger.py
robin_sd_upload/supportive_scripts/remove_zip.py
robin_sd_upload/supportive_scripts/sudo_file.py
robin_sd_upload/supportive_scripts/validate.py
robin_sd_upload/supportive_scripts/version_checker.py
robin_sd_upload/supportive_scripts/yaml_parser.py
tests/__init__.py
tests/test.py
robin_sd_upload-0.2.54.dist-info/METADATA
robin_sd_upload-0.2.54.dist-info/WHEEL
robin_sd_upload-0.2.54.dist-info/entry_points.txt
robin_sd_upload-0.2.54.dist-info/top_level.txt
robin_sd_upload-0.2.54.dist-info/RECORD
