Metadata-Version: 2.1
Name: robin-sd-upload
Version: 0.2.54
Summary: Package to upload files to the Robin Radar API
Home-page: https://bitbucket.org/robin-radar-systems/sd-api-upload-pip-package.git
Author: Robin Radar Systems
Author-email: it-team@robinradar.com
License: MIT
Keywords: python,robin,radar,upload,software,sd
Platform: UNKNOWN
Requires-Dist: validators
Requires-Dist: requests
Requires-Dist: pyYAML
Requires-Dist: zipfile36
Requires-Dist: slack-sdk
Requires-Dist: pypi-simple
